jupyno/__init__.py
jupyno/jupyno.py
jupyno-1.0.4.dist-info/LICENCE
jupyno-1.0.4.dist-info/METADATA
jupyno-1.0.4.dist-info/WHEEL
jupyno-1.0.4.dist-info/top_level.txt
jupyno-1.0.4.dist-info/RECORD
